LICENSE
README.md
setup.cfg
setup.py
clouduniqueid/__init__.py
clouduniqueid.egg-info/PKG-INFO
clouduniqueid.egg-info/SOURCES.txt
clouduniqueid.egg-info/dependency_links.txt
clouduniqueid.egg-info/top_level.txt
clouduniqueid/clouds/__init__.py
clouduniqueid/clouds/aws/__init__.py
clouduniqueid/clouds/aws/uniqueid.py
clouduniqueid/clouds/azure/__init__.py
clouduniqueid/clouds/bitbucket/__init__.py
clouduniqueid/clouds/bitbucket/uniqueid.py
clouduniqueid/clouds/gcp/__init__.py
clouduniqueid/clouds/gcp/uniqueid.py
tests/test_aws.py
tests/test_azure.py
tests/test_bitbucket.py
tests/test_gcp.py