Metadata-Version: 2.1
Name: clouduniqueid
Version: 1.0.3
Summary: Generate unique id for cloud resources
Home-page: https://github.com/Cloudanix/clouduniqueid
Maintainer: Cloudanix
Maintainer-email: ganesh@cloudanix.com
License: apache2
Classifier: Programming Language :: Python :: 3
Classifier: Intended Audience :: Developers
Classifier: License :: OSI Approved :: Apache Software License
Classifier: Natural Language :: English
Classifier: Operating System :: OS Independent
License-File: LICENSE
